<?xml version="1.0" encoding="UTF-8"?>

<!DOCTYPE sect3 PUBLIC "-//OASIS//DTD DocBook XML V4.3//EN"
                "http://www.docbook.org/xml/4.3/docbookx.dtd">

<!-- section history:
  2007-10-10 j.h : updated en;fr to v2.4
-->
<sect3 id="gimp-edit-paste-as-new" lang="en;cs;de;es;fr;it;no;zh_CN">
  <sect3info lang="en;cs;de;es;fr;no" role="cvs">
    <revhistory>
      <revision lang="en">
        <revnumber>$Revision$</revnumber>
        <date>2006-07-27</date>
        <authorinitials>scb</authorinitials>
      </revision>
      <revision lang="cs">
        <revnumber>$Revision$</revnumber>
        <date>2006-02-08</date>
        <authorinitials>jfriedl</authorinitials>
      </revision>
      <revision lang="de">
        <revnumber>$Revision$</revnumber>
        <date>2007-10-15</date>
        <authorinitials>ude</authorinitials>
      </revision>
      <revision lang="es">
        <revnumber>$Revision$</revnumber>
        <date>2006-11-22</date>
        <authorinitials>manuq</authorinitials>
      </revision>
      <revision lang="fr">
        <revnumber>$Revision$</revnumber>
        <date>2006-07-03</date>
        <authorinitials>j.h</authorinitials>
      </revision>
      <revision lang="no">
        <revnumber>$Revision$</revnumber>
        <date>2007-02-09</date>
        <authorinitials>KoSt</authorinitials>
      </revision>
    </revhistory>
  </sect3info>

  <title>
    <phrase lang="en">Paste as New Image</phrase>
    <phrase lang="cs">Vložit jako nový</phrase>
    <phrase lang="de">Als neues Bild einfügen</phrase>
    <phrase lang="es">Pegar como nuevo</phrase>
    <phrase lang="fr">Coller en tant que nouvelle image</phrase>
    <phrase lang="it">Incolla come nuova immagine</phrase>
    <phrase lang="no">Lim inn som ny</phrase>
    <phrase lang="zh_CN">粘贴为新图像</phrase>
  </title>

<!-- TODO: update cs, de, es, no, zh_CN indexterms -->

  <indexterm lang="en">
    <primary>Layer</primary>
    <secondary>Paste</secondary>
  </indexterm>
  <indexterm lang="en">
    <primary>Selection</primary>
    <secondary>Paste</secondary>
    </indexterm>
  <indexterm lang="en">
    <primary>Paste as new image</primary>
  </indexterm>

  <indexterm lang="cs">
    <primary>Vložit jako nový obrázek</primary>
  </indexterm>

  <indexterm lang="de"><primary>Zwischenablage</primary></indexterm>

  <indexterm lang="es">
    <primary>Pegar como nuevo</primary>
  </indexterm>

  <indexterm lang="fr">
    <primary>Calque</primary>
    <secondary>Coller</secondary>
  </indexterm>
  <indexterm lang="fr">
    <primary>Sélection</primary>
    <secondary>Coller</secondary>
  </indexterm>
  <indexterm lang="fr">
    <primary>Coller en tant que nouvelle image</primary>
  </indexterm>

  <indexterm lang="it">
    <primary>Livello</primary>
    <secondary>Incolla</secondary>
  </indexterm>
  <indexterm lang="it">
    <primary>Selezione</primary>
    <secondary>Incolla</secondary>
    </indexterm>
  <indexterm lang="it">
    <primary>Incolla come nuova immagine</primary>
  </indexterm>

  <indexterm lang="no">
    <primary>Lim inn som ny</primary>
  </indexterm>

  <indexterm lang="zh_CN">
    <primary>粘贴为新图像</primary>
  </indexterm>


  <para lang="en">
    The <guimenuitem>Paste As New Image</guimenuitem> command creates a new
    image and pastes the image data from the Clipboard into it. If the data
    is not rectangular or square in shape, any regions that do not extend to
    the edge of the canvas are left transparent (an Alpha channel is
    automatically created). Of course, you have to Copy your selection before
    you use this command, so that you get an image with the same dimensions
    as the selection.
  </para>
  <para lang="cs">
    Data vložená ze schránky příkazem Vložit jako nový obrázek vytvoří nový
    obrázek v novém okně obsahující data ze schránky. Pokud vložená obrazová
    data netvoří čtverec nebo obdélník, jsou doplněna průhlednými oblastmi.
    Obrazová data musíte před použitím příkazu do schránky zkopírovat nebo
    vyjmout. Příkaz se hodí pro vytvoření nového obrázku s rozměry přesně
    odpovídajícími rozměrům výběru.
  </para>
  <para lang="de">
    Jedes Bildobjekt, welches mit <guimenuitem>Als neues Bild
    einfügen</guimenuitem> aus der Zwischenablage eingefügt wird,
    bekommt ein eigenes Bildfenster.
  </para>
  <para lang="es">
    El comando <guimenuitem>Pegar como nuevo</guimenuitem> crea una nueva
    imagen y pega los datos de la papelera sobre ella.  Si estos datos no
    tienen forma rectangular ni cuadrada, las regiones que no se extienden
    hasta el borde del lienzo se dejan transparentes (se crea un canal alfa
    automáticamente).  Por supuesto, tiene que copiar su selección antes de
    emplear este comando, y así obtener una imagen con las dimensiones justas
    para contener a la selección.
  </para>
  <para lang="fr">
    Avec cette commande, tout ce qui est dans le presse-papier sera collé
    dans une nouvelle image créée pour l'occasion. Si les données collées ne
    remplissent pas complètement le canevas parce qu'elles ne sont pas
    rectangulaires, les espaces vides seront laissés transparents (un canal
    Alpha est sytématiquement créé). Bien entendu, une sélection devra être
    copiée avant d'utiliser cette commande, qui permet d'avoir une image aux
    dimensions exactes de la sélection.
  </para>
  <para lang="it">
    Il comando <guimenuitem>Incolla come nuova immagine</guimenuitem> crea
    una nuova immagine e vi incolla i dati grafici presenti negli
    appunti. Se i dati non hanno una forma quadrata o rettangolare,
    qualsiasi regione che non si estende esattamente fino al bordo
    dell'area disegnabile, viene lasciata trasparente (e viene creato
    automaticamente un canale alfa). Per ottenere un'immagine delle stesse
    dimensioni della selezione, è necessario copiare la selezione prima di
    usare il comando.
  </para>
  <para lang="no">
    Kommandoen <guimenuitem>Lim inn som ny</guimenuitem> oppretter eit
    nytt biletvindauge og limer det som måtte finnast på utklippstavla inn i
    dette.
    Dersom utklippet ikkje er firkanta, vil alle områda som ikkje rekk ut til
    ramma bli markerte som gjennomsiktige. Det blir i tilfelle laga ein
    alfakanal automatisk.
  </para>

  <para lang="zh_CN">
    粘贴为新图像命令就是将剪贴板的内容做成新图像。如果粘贴的图像不是矩形或正
    方形，那么底图中粘贴数据没覆盖的部分保持透明。当然，在使用这个命令前，您
    必须先选择您的复制区域，这样才能允许您得到一个和选择区大小一致的图像。
  </para>


  <sect4>
    <title>
      <phrase lang="en">Activating the Command</phrase>
      <phrase lang="cs">Aktivace dialogu</phrase>
      <phrase lang="de">Aufruf des Kommandos</phrase>
      <phrase lang="es">Activación del comando</phrase>
      <phrase lang="fr">Appel de la commande</phrase>
      <phrase lang="it">Attivazione del comando</phrase>
      <phrase lang="no">Aktivering</phrase>
      <phrase lang="zh_CN">开启对话框</phrase>
    </title>

    <itemizedlist><!--TODO es;no;ru; v2.4-->
      <listitem>
        <para lang="en">
          You can access this command from the image menubar through
          <menuchoice>
            <guimenu><accel>E</accel>dit</guimenu>
            <guisubmenu>Paste as</guisubmenu>
            <guimenuitem>New Image</guimenuitem>
          </menuchoice>.
        </para>
        <para lang="cs">
          Tento příkaz je dostupný z nabídky obrázku volbou
          <menuchoice>
            <guimenu>Upravit</guimenu>
            <guimenuitem>Vložit jako nový obrázek</guimenuitem>
          </menuchoice>
        </para>
        <para lang="de">
          Der Menüeintrag kann aus dem Bildfenster erreicht werden:
          <menuchoice>
            <guimenu>Bearbeite<accel>n</accel></guimenu>
            <guisubmenu>Einfügen als</guisubmenu>
            <guimenuitem>Neues Bild</guimenuitem>
          </menuchoice>.
        </para>
        <para lang="es">
          Puede acceder a este comando desde la barra de menú de la imagen,
          siguiendo:
          <menuchoice>
            <guimenu><accel>E</accel>ditar</guimenu>
            <guimenuitem>Pegar como <accel>n</accel>uevo</guimenuitem>
          </menuchoice>.
        </para>
        <para lang="fr">
          On accède à cette commande à partir de la barre de menu de l'image
          par
          <menuchoice>
            <guimenu><accel>É</accel>dition</guimenu>
            <guisubmenu>Coller comme</guisubmenu>
            <guimenuitem>Nouvelle image</guimenuitem>
          </menuchoice>
        </para>
        <para lang="fr">
          Le nom anglais de cette commande est <quote>Paste as New</quote>.
        </para>
        <para lang="it">
          È possibile accedere al comando dalla barra del menu immagine
          tramite
          <menuchoice>
            <guimenu><accel>M</accel>odifica</guimenu>
            <guisubmenu><accel>I</accel>ncolla come</guisubmenu>
            <guimenuitem><accel>N</accel>uova immagine</guimenuitem>
          </menuchoice>.
        </para>
        <para lang="no">
          Du får tilgang til denne undermenyen på biletmenyen via
          <menuchoice>
            <guimenu>Rediger</guimenu>
            <guimenuitem>Lim inn som ny</guimenuitem>
          </menuchoice>.
        </para>
        <para lang="zh_CN">
          这个命令可以在<guimenuitem>图像&gt;编辑/粘贴为新图像</guimenuitem>找到。
        </para>
      </listitem>
    </itemizedlist>
  </sect4>
</sect3>
