<?xml version="1.0" encoding="UTF-8" ?>

<!DOCTYPE sect2 PUBLIC "-//OASIS//DTD DocBook XML V4.3//EN"
                "http://www.docbook.org/xml/4.3/docbookx.dtd">

<!-- section history:
  2007-03-12 Kolbjørn: added no translation
  2005/11/11 reviewed and split into one file per command by axel.wernicke
-->
<sect2 id="gimp-layer-mask-menu" lang="en;cs;de;fr;it;no;zh_CN">
  <sect2info lang="en;de;fr;no" role="cvs">
    <revhistory>
      <revision lang="en">
        <revnumber>$Revision$</revnumber>
        <date>2006-08-18</date>
        <authorinitials>scb</authorinitials>
      </revision>
      <revision lang="de">
        <revnumber>$Revision$</revnumber>
        <date>2007-04-01</date>
        <authorinitials>ude</authorinitials>
      </revision>
      <revision lang="fr">
        <revnumber>$Revision$</revnumber>
        <date>2006-08-05</date>
        <authorinitials>j.h</authorinitials>
      </revision>
      <revision lang="no">
        <revnumber>$Revision$</revnumber>
        <date>2007-02-24</date>
        <authorinitials>KoSt</authorinitials>
      </revision>
    </revhistory>
  </sect2info>
  
  <title>
    <phrase lang="en">The <quote>Mask</quote> Submenu</phrase>
    <phrase lang="cs">Maska</phrase>
    <phrase lang="de">Das Untermenü <quote>Maske</quote></phrase>
    <phrase lang="fr">Le sous-menu <quote>Masque</quote></phrase>
    <phrase lang="it">Il sottomenu <quote>Maschera</quote></phrase>
    <phrase lang="no">Undermenyen <quote>Masker</quote></phrase>
    <phrase lang="zh_CN">蒙板</phrase>
  </title>

  <indexterm lang="en">
    <primary>Layer</primary>
    <secondary>Sub-menu</secondary>
    <tertiary>Mask</tertiary>
  </indexterm>
  <indexterm lang="de">
    <primary>Maske</primary>
  </indexterm>
  <indexterm lang="fr">
    <primary>Calque</primary>
    <secondary>Sous-menu</secondary>
    <tertiary>Masque</tertiary>
  </indexterm>
  <indexterm lang="it">
    <primary>Livello</primary>
    <secondary>Sottomenu</secondary>
    <tertiary>Maschera</tertiary>
  </indexterm>
  <indexterm lang="no">
    <primary>Lagmenyen</primary>
    <secondary>Masker</secondary>
  </indexterm>
  <indexterm lang="no"><primary>Masker</primary></indexterm>

  <figure>
    <title>
      <phrase lang="en">
        The <quote>Mask</quote> submenu of the <quote>Layer</quote> menu
      </phrase>
      <phrase lang="cs">Podnabídka Maska nabídky Vrstva okna obrázku</phrase>
      <phrase lang="de">Das Untermenü <quote>Maske</quote></phrase>
      <phrase lang="fr">Le sous-menu Masque du menu Calques</phrase>
      <phrase lang="it">
        Il sottomenu <quote>maschera</quote> del menu
        <quote>livello</quote></phrase>
      <phrase lang="no">
        Undermenyen <quote>Masker</quote> i menyen <quote>Lag</quote>
      </phrase>
      <phrase lang="zh_CN">图层菜单的蒙板子菜单</phrase>
    </title>
    <mediaobject>
      <imageobject lang="en;cs">
        <imagedata fileref="../images/menus/menus-layer-mask.png"
          format="PNG" />
      </imageobject>
      <imageobject lang="de">
        <imagedata fileref="../images/menus/de/menus-layer-mask.png"
          format="PNG" />
      </imageobject>
      <imageobject lang="fr">
        <imagedata fileref="../images/menus/fr/menus-layer-mask.png"
          format="PNG" />
      </imageobject>
      <imageobject lang="it">
        <imagedata fileref="../images/menus/it/menus-layer-mask.png"
          format="PNG" />
      </imageobject>
      <imageobject lang="no">
        <imagedata fileref="../images/menus/no/menus-layer-mask.png"
          format="PNG" />
      </imageobject>
      <imageobject lang="zh_CN">
        <imagedata fileref="../images/menus/zh_CN/menus-layer-mask.png"
          format="PNG" />
      </imageobject>
    </mediaobject>
  </figure>

  <para lang="en">
    The <guimenu>Mask</guimenu> submenu of the <guimenu>Layer</guimenu>
    menu contains commands which work with masks: creating a mask, applying
    a mask, deleting a mask or converting a mask into a selection. See the
    <link linkend="gimp-layer-mask">Layer Masks</link>
    section for more information on layer masks and how to use them.
  </para>
  <para lang="cs">
    Podnabídka <guisubmenu>Maska</guisubmenu> nabídky
    <guimenu>Vrstva</guimenu>
    obsahuje operace ovlivňující masku vrstvy. The Mask submenu of the Layers
    menu contains operations that involve a layer mask: creating one, applying
    one, deleting one, or converting one into a selection. See the
    <link linkend="gimp-layer-mask">Layer Masks</link>
    section for more information on layer masks and how to use them.
  </para>
  <para lang="de">
    In diesem Untermenü finden Sie verschiedene Kommandos, um mit Masken zu
    arbeiten. Informationen, wie Ebenenmasken in <acronym>GIMP</acronym>
    eingesetzt werden können, finden Sie im <xref linkend="gimp-layer-mask"/>.
  </para>
  <para lang="fr">
    Le sous-menu Masque du menu Calques contient des commandes concernant les
    masques de calque : Ajouter, Appliquer, Effacer ou Convertir en sélection
    un masque de calque. Voir <link linkend="gimp-layer-mask">masques de
    calques</link> pour plus d'information sur les masques de calques et la
    façon de les utiliser.
  </para>
  <para lang="it">
    Il sottomenu <guimenu>maschera</guimenu> del menu
    <guimenu>livello</guimenu> contiene i comandi che lavorano con le
    maschere di livello: creazione di una maschera, applicazione di una
    maschera, eliminazione di una maschera o conversione di una maschera in
    una selezione. Vedere la sezione <link
    linkend="gimp-layer-mask">maschere di livello</link> per ulteriori
    informazioni sulle maschere di livello e su come utilizzarle.
  </para>
  <para lang="no">
    Undermenyen <guimenu>Masker</guimenu> i 
    <guimenu>Lag</guimenu>-menyen inneheld kommandoar som verkar på
    lagmasker. Med dei ulike innslaga kan du opprette masker, arbeide på
    masker, fjerne masker eller omforme ei maske til ei markering. Sjå meir
    om dette under <link 
    linkend="gimp-layer-mask">Lagmasker</link>.
  </para>
  <para lang="zh_CN">
    图层菜单的蒙板子菜单包括与图层蒙板相关的操作：新建，应用，删除和转变为选
    区。关于图层蒙板以及如何使用它的更多信息请看<link
    linkend="gimp-layer-mask">图层蒙板</link> 章节。
  </para>

  <sect3 lang="en;de;fr;it;no">
    <title>
      <phrase lang="en">Activating the Submenu</phrase>
      <phrase lang="cs">Aktivace dialogu</phrase>
      <phrase lang="de">Aufruf des Untermenüs</phrase>
      <phrase lang="fr">Activer le sous-menu</phrase>
      <phrase lang="it">Attivazione del sottomenu</phrase>
      <phrase lang="no">Aktivering</phrase>
      <phrase lang="zh_CN">开启对话框</phrase>
    </title>

    <itemizedlist>
      <listitem>
        <para lang="en">
          You can access this submenu from the image menubar through
          <menuchoice>
            <guimenu><accel>L</accel>ayer</guimenu>
            <guimenuitem><accel>M</accel>ask</guimenuitem>
          </menuchoice>.
        </para>
        <para lang="de">
          Das Untermenü kann aus dem Bildfenster erreicht werden:
          <menuchoice>
            <guimenu><accel>E</accel>bene</guimenu>
            <guimenuitem><accel>M</accel>aske</guimenuitem>
          </menuchoice>.
        </para>
        <para lang="fr">
          Vous le trouverez dans
          <menuchoice>
            <guimenu><accel>C</accel>alque</guimenu>
            <guimenuitem><accel>M</accel>asque</guimenuitem>
          </menuchoice>.
        </para>
        <para lang="it">
          È possibile accederea a questo sottomenu dalla barra del menu
          immagine tramite
          <menuchoice>
            <guimenu><accel>L</accel>ivello</guimenu>
            <guimenuitem><accel>M</accel>aschera</guimenuitem>
          </menuchoice>.
        </para>
        <para lang="no">
          Du har tilgang til denne undermenyen på biletmenyen via
          <menuchoice>
            <guimenu>Lag</guimenu>
            <guimenuitem>Masker</guimenuitem>
          </menuchoice>.
        </para>
      </listitem>
    </itemizedlist>
  </sect3>

  <sect3>
    <title>
      <phrase lang="en;zh_CN">
        The Contents of the <quote>Mask</quote> Submenu
      </phrase>
      <phrase lang="de">Der Inhalt des Untermenüs</phrase>
      <phrase lang="fr">Contenu du sous-menu</phrase>
      <phrase lang="it">
        I contenuti del sottomenu <quote>Maschera</quote>
      </phrase>
      <phrase lang="no">Innhald i undermenyen</phrase>
    </title>

    <para lang="en">
      The <guimenu>Mask</guimenu> submenu contains the following commands:
    </para>
    <para lang="de">
      Im Untermenü <guisubmenu>Maske</guisubmenu> stehen Ihnen folgende
      Kommandos zur Verfügung:
    </para>
    <para lang="fr">
      Le sous-menu <guilabel>Masque</guilabel> contient les commandes
      suivantes:
    </para>
    <para lang="it">
      Il sottomenu <guimenu>maschera</guimenu> contiene i seguenti comandi:
    </para>
    <para lang="no">
        Kommandoane i undermenyen <quote>Masker</quote>:
    </para>

    <itemizedlist>
      <listitem>
        <para>
          <xref linkend="gimp-layer-mask-add" />
        </para>
      </listitem>
      <listitem>
        <para>
          <xref linkend="gimp-layer-mask-apply" />
        </para>
      </listitem>
      <listitem>
        <para>
          <xref linkend="gimp-layer-mask-delete" />
        </para>
      </listitem>
      <listitem lang="en;fr;it;no">
        <para>
          <xref linkend="gimp-layer-mask-show" />
        </para>
      </listitem>
      <listitem lang="en;fr;it;no">
        <para>
          <xref linkend="gimp-layer-mask-edit" />
        </para>
      </listitem>
      <listitem lang="en;fr;it;no">
        <para>
          <xref linkend="gimp-layer-mask-disable" />
        </para>
      </listitem>
      <listitem>
        <para>
          <xref linkend="gimp-layer-mask-selection-replace" />
        </para>
      </listitem>
      <listitem lang="en;de;fr;it;no;zh_CN">
        <para>
          <xref linkend="gimp-layer-mask-selection-add" />
        </para>
      </listitem>
      <listitem lang="en;de;fr;it;no;zh_CN">
        <para>
          <xref linkend="gimp-layer-mask-selection-subtract" />
        </para>
      </listitem>
      <listitem lang="en;de;fr;it;no;zh_CN">
        <para>
          <xref linkend="gimp-layer-mask-selection-intersect" />
        </para>
      </listitem>
    </itemizedlist>
  </sect3>
</sect2>
