<?xml version='1.0' encoding="UTF-8" ?>

<sect1 id='gimp-dialog-menus' xmlns:xi="http://www.w3.org/2001/XInclude">
  <title lang="en">Image Menus</title>
  <title lang="de">Im Menü aufzufindene Dialoge</title>
  <title lang="fr">Menus</title>
  <indexterm>
    <primary lang="en">Menu</primary>
    <primary lang="de">Menü</primary>
    <primary lang="fr">Menu</primary>
  </indexterm>
  
  <sect2 id='gimp-using-imagewindow-menus-file'>
    <title lang="en">File</title>
    <title lang="de">Datei</title>
    <title lang="fr">Fichier</title>
    <indexterm>
      <primary lang="en">Image menu file</primary>
      <primary lang="de">Bildmenü Datei</primary>
      <primary lang="fr">Image menu fichier</primary>
    </indexterm>
    <xi:include href="menus/file-new.xml" />    
    <xi:include href="menus/file-open.xml" />    
    <xi:include href="menus/file-open-recent.xml" />    
    <xi:include href="menus/file-save.xml" />    
    <xi:include href="menus/file-save-as.xml" />    
  </sect2>
  
  <sect2>
    <title lang="en">Edit</title>
    <title lang="de">Bearbeiten</title>
    <title lang="fr">Édition</title>
    <indexterm>
      <primary lang="en">Image menu edit</primary>
      <primary lang="de">Bildmenü Bearbeiten</primary>
      <primary lang="fr">Image menu édition</primary>
    </indexterm>
    <xi:include href="menus/edit-undo.xml" />
    <xi:include href="menus/edit-redo.xml" />
    <xi:include href="menus/edit-undo-history.xml" />
    <xi:include href="menus/edit-cut.xml" />
    <xi:include href="menus/edit-copy.xml" />
    <xi:include href="menus/edit-paste.xml" />
    <xi:include href="menus/edit-paste-into.xml" />
    <xi:include href="menus/edit-paste-as-new.xml" />
    <xi:include href="menus/edit-buffer-dialog.xml" />
    <xi:include href="menus/edit-clear.xml" />
    <xi:include href="menus/edit-fill.xml" />
    <xi:include href="menus/edit-stroke-path.xml" />
    <xi:include href="menus/edit-stroke-selection.xml" />
    <xi:include href="menus/edit-copy-visible.xml" />    
  </sect2>
 
  <sect2>
    <title lang="en">Select</title>
    <title lang="fr">Sélection</title>
    <indexterm>
      <primary lang="en">Image menu select</primary>
      <primary lang="fr">Image menu sélection</primary>
    </indexterm>
    <xi:include href="menus/select-all.xml" />    
    <xi:include href="menus/select-none.xml" />    
    <xi:include href="menus/select-invert.xml" />   
    <xi:include href="menus/select-from-path.xml" />    
    <xi:include href="menus/select-float.xml" />    
    <xi:include href="menus/select-bycolor.xml" />    
    <xi:include href="menus/select-feather.xml" />   
    <xi:include href="menus/select-sharpen.xml" />    
    <xi:include href="menus/select-shrink.xml" />    
    <xi:include href="menus/select-grow.xml" /> 
    <xi:include href="menus/select-border.xml" />    
    <xi:include href="menus/select-toggle-qmask.xml" />   
    <xi:include href="menus/select-save-to-channel.xml" />    
    <xi:include href="menus/select-to-path.xml" />   
  </sect2> 
  
  <sect2 id='gimp-imagewindow-menus-view'>
    <title lang="en">View</title>
    <title lang="fr">Affichage</title>
    <indexterm>
      <primary lang="en">Image menu view</primary>
      <primary lang="fr">Image menu affichage</primary>
    </indexterm>
    <xi:include href="menus/view-new-view.xml" />    
    <xi:include href="menus/view-dot-for-dot.xml" />    
    <xi:include href="menus/view-zoom.xml" />    
    <xi:include href="menus/view-infowindow.xml" />    
    <xi:include href="menus/view-navigwindow.xml" />    
    <xi:include href="menus/view-show-selection.xml" />
    <!-- 20040702-->
    <xi:include href="menus/view-show-layer-boundary.xml" />
    <!--end-->
    <xi:include href="menus/view-show-guides.xml" />
    <xi:include href="menus/view-snap-to-guides.xml" />
    <xi:include href="menus/view-show-grid.xml" />
    <xi:include href="menus/view-snap-to-grid.xml" />
    <xi:include href="menus/view-show-menubar.xml" />
    <xi:include href="menus/view-show-rulers.xml" />
    <xi:include href="menus/view-show-scrollbars.xml" />
    <xi:include href="menus/view-show-statusbar.xml" />
    <xi:include href="menus/view-shrinkwrap.xml" />
    <xi:include href="menus/view-fullscreen.xml" />
  </sect2> 
  
  <sect2>
    <title lang="en">Image</title>
    <title lang="fr">Image</title>
    <indexterm>
      <primary lang="en">Image menu image</primary>
      <primary lang="fr">Image menu image</primary>
    </indexterm>
    <xi:include href="menus/image-mode.xml" />
    <xi:include href="menus/image-transform.xml" />
    <xi:include href="menus/image-canvas-size.xml" />
    <xi:include href="menus/image-scale.xml" />
    <xi:include href="menus/image-duplicate.xml" />
    <xi:include href="menus/image-merge-vlayers.xml" />
    <xi:include href="menus/image-flatten-image.xml" />    
    <xi:include href="menus/image-configure-grid.xml" />
  </sect2>

  <sect2>
    <title lang="en">Layers</title>
    <title lang="fr">Calques</title>
    <indexterm>
      <primary lang="en">Image menu layer</primary>
      <primary lang="fr">Image menu calque</primary>
    </indexterm>
    <xi:include href="menus/layer.xml" />
  </sect2>

  <sect2>
    <title lang="en">Tools</title>
    <title lang="fr">Outils</title>
    <indexterm>
      <primary lang="en">Image menu tools</primary>
      <primary lang="fr">Image menu outils</primary>
    </indexterm>
    <xi:include href="menus/tools.xml" />
  </sect2>
  
</sect1>
