<?xml version="1.0" encoding="UTF-8"?>
<!DOCTYPE sect2 PUBLIC "-//OASIS//DTD DocBook XML V4.3//EN"
                       "http://www.docbook.org/xml/4.3/docbookx.dtd">
<!-- section history:
  2017-04-02 elle stone: added updated screenshot
  2007-09-26 AntI: Added 'es'
  2007-03-12 alex falappa: added it translation
  2005-10-24 de created by axel.wernicke
-->
<sect2 xmlns:xi="http://www.w3.org/2001/XInclude" id="gimp-image-menu-overview">
  <title>Overview</title>

  <indexterm>
    <primary>Menus</primary>
    <secondary>Image</secondary>
  </indexterm>

  <para>
    In this section, you will find help for commands in the
    <menuchoice><guimenu>Image</guimenu></menuchoice> menu, which includes
    commands that use or affect the entire image in some way, not just the
    active layer or a specific part of the image.
  </para>
  <xi:include href="../about-plugin-menuitems.xml"/>

  <sect3>
    <title>The Contents of the <quote>Image</quote> Menu</title>
    <itemizedlist>
      <listitem>
        <para><xref linkend="gimp-image-duplicate"/></para>
      </listitem>
      <listitem>
        <para><xref linkend="gimp-image-mode"/></para>
      </listitem>
      <listitem>
        <para><xref linkend="gimp-image-convert-rgb"/></para>
      </listitem>
      <listitem>
        <para><xref linkend="gimp-image-convert-grayscale"/></para>
      </listitem>
      <listitem>
        <para><xref linkend="gimp-image-convert-indexed"/></para>
      </listitem>
      <listitem>
        <para><xref linkend="gimp-image-encoding"/></para>
      </listitem>
      <listitem>
        <para><xref linkend="gimp-image-color-management"/></para>
      </listitem>
      <listitem>
        <para><xref linkend="gimp-image-color-profile-use-srgb"/></para>
      </listitem>
      <listitem>
        <para><xref linkend="gimp-image-color-profile-assign"/></para>
      </listitem>
      <listitem>
        <para><xref linkend="gimp-image-color-profile-convert"/></para>
      </listitem>
      <listitem>
        <para><xref linkend="gimp-image-color-profile-discard"/></para>
      </listitem>
      <listitem>
        <para><xref linkend="gimp-image-color-profile-save"/></para>
      </listitem>
      <listitem>
        <para><xref linkend="gimp-image-soft-proof-profile-assign"/></para>
      </listitem>
      <listitem>
        <para><xref linkend="gimp-image-soft-proof-rendering-intent"/></para>
      </listitem>
      <listitem>
        <para><xref linkend="gimp-image-soft-proof-black-point"/></para>
      </listitem>
      <listitem>
        <para><xref linkend="gimp-image-transform"/></para>
      </listitem>
      <listitem>
        <para><xref linkend="gimp-image-flip-horizontal"/></para>
      </listitem>
      <listitem>
        <para><xref linkend="gimp-image-rotate-90"/></para>
      </listitem>
      <listitem>
        <para><xref linkend="gimp-image-resize"/></para>
      </listitem>
      <listitem>
        <para><xref linkend="gimp-image-resize-to-layers"/></para>
      </listitem>
      <listitem>
        <para><xref linkend="gimp-image-resize-to-selection"/></para>
      </listitem>
      <listitem>
        <para><xref linkend="gimp-image-print-size"/></para>
      </listitem>
      <listitem>
        <para><xref linkend="gimp-image-scale"/></para>
      </listitem>
      <listitem>
        <para><xref linkend="gimp-image-crop"/></para>
      </listitem>
      <listitem>
        <para><xref linkend="plug-in-guillotine"/></para>
      </listitem>
      <listitem>
        <para><xref linkend="plug-in-zealouscrop"/></para>
      </listitem>
      <listitem>
        <para><xref linkend="gimp-image-merge-layers"/></para>
      </listitem>
      <listitem>
        <para><xref linkend="gimp-image-flatten"/></para>
      </listitem>
      <listitem>
        <para><xref linkend="plug-in-align-layers"/></para>
      </listitem>
      <listitem>
        <para><xref linkend="gimp-image-guides"/></para>
      </listitem>
      <listitem>
        <para><xref linkend="script-fu-guide-new-percent"/></para>
      </listitem>
      <listitem>
        <para><xref linkend="script-fu-guide-new"/></para>
      </listitem>
      <listitem>
        <para><xref linkend="script-fu-guides-from-selection"/></para>
      </listitem>
      <listitem>
        <para><xref linkend="script-fu-guides-remove"/></para>
      </listitem>
      <listitem>
        <para><xref linkend="gimp-image-configure-grid"/></para>
      </listitem>
      <listitem>
        <para><xref linkend="gimp-image-properties"/></para>
      </listitem>
      <listitem>
        <para><xref linkend="gimp-image-metadata"/></para>
      </listitem>
      <listitem>
        <para><xref linkend="plug-in-metadata-editor"/></para>
      </listitem>
      <listitem>
        <para><xref linkend="plug-in-metadata-viewer"/></para>
      </listitem>
    </itemizedlist>
  </sect3>

</sect2>
