<?xml version="1.0" encoding="UTF-8"?>
<!DOCTYPE sect2 PUBLIC "-//OASIS//DTD DocBook XML V4.3//EN"
                       "http://www.docbook.org/xml/4.3/docbookx.dtd">
<!-- section history:
  2009-02-22 ude: adapted Axel's (German) example
  2009-01-16 j.h: reviewed for v2.6
  2005/10/17 reviewed; de added by axel.wernicke
-->
<sect2 id="gimp-view-dot-for-dot">
  <title>Dot for Dot</title>

  <indexterm>
    <primary>Display</primary>
    <secondary>Dot for Dot</secondary>
  </indexterm>
  <indexterm>
    <primary>Dot for Dot</primary>
  </indexterm>

  <para>
    The <guimenuitem>Dot for Dot</guimenuitem> command enables and disables
    <quote>Dot for Dot</quote> mode. If it is enabled (checked) and the
    zoom factor is 100%, every pixel in the image is displayed as one pixel
    on the screen. If it is disabled, the image is displayed at its
    <quote>real</quote> size, the size it will have when it is printed.
  </para>
  <para>
    For Dot for Dot mode to work properly, the resolution of the image
    must be the same as the screen resolution in the
    <link linkend="gimp-prefs-display">Preferences menu</link>.
  </para>
  <para>
    Enabling this mode is recommended if you are working on icons and web
    graphics. If you are working on images intended to be printed, you should
    disable Dot-for-Dot mode.
  </para>
  <para>
    You can set the default for Dot-for-Dot mode in the
    <link linkend="gimp-prefs-image-window-appearance">Image Window Appearance Preferences</link>.
  </para>

  <sect3>
    <title>Activating the Command</title>
    <itemizedlist>
      <listitem>
        <para>
          You can access this command from the main menu through
          <menuchoice>
            <guimenu>View</guimenu>
            <guimenuitem>Dot for Dot</guimenuitem>
          </menuchoice>.
        </para>
      </listitem>
    </itemizedlist>
  </sect3>
  <sect3>
  <title>Example</title>
  <para>
    Imagine the following image properties:
  </para>
  <itemizedlist>
    <listitem>
      <para>Image size: 100×100 pixels</para>
    </listitem>
    <listitem>
      <para>Image resolution: 300 ppi (pixels per inch)</para>
    </listitem>
    <listitem>
      <para>
        Image displayed with Zoom=100%, <quote>Dot for Dot</quote>
        <emphasis>enabled</emphasis>:
      </para>
      <blockquote><para>100×100 pixels</para></blockquote>
    </listitem>
    <listitem>
      <para>
        Image displayed with Zoom=100%, <quote>Dot for Dot</quote>
        <emphasis>disabled</emphasis>:
      </para>
      <blockquote>
        <para>
          100 pixels &divide; 300 ppi = 1/3 inch &cong; 0.85 cm
        </para>
      </blockquote>
    </listitem>
  </itemizedlist>
  </sect3>
</sect2>
