<?xml version="1.0" encoding="UTF-8"?>
<!DOCTYPE sect2 PUBLIC "-//OASIS//DTD DocBook XML V4.5//EN"
                       "http://www.docbook.org/xml/4.5/docbookx.dtd">
<!-- section history:
  2017-03-08 j.h: created
-->
<sect2 id="gimp-view-color-management">
  <title>Color Management</title>

  <note>
    <para>
      For color profile related actions of an image file, see
      <xref linkend="gimp-image-color-management"/>.
    </para>
    <para>
      For <acronym>GIMP</acronym>'s general Color Management
      preferences, see <xref linkend="gimp-prefs-color-management"/>.
    </para>
  </note>

  <indexterm>
    <primary>Color Management</primary>
  </indexterm>

  <para>
    This menu item opens a submenu allowing you to manage color
    display management on your system.
    These settings only affect the current display of an image. You can have
    multiple views of an image, each with their own color management view
    settings.
  </para>

  <sect3>
    <title>Activating the Submenu</title>
    <para>
      You can access this submenu from the main menu through
      <menuchoice>
        <guimenu>View</guimenu>
        <guimenuitem>Color Management</guimenuitem>
      </menuchoice>.
    </para>
  </sect3>

  <sect3>
    <title>The Contents of the <quote>Color Management</quote> Submenu</title>
    <itemizedlist>
      <listitem>
        <para>
          <link linkend="gimp-view-color-manage-view">Color-Manage this View</link>
        </para>
      </listitem>
      <listitem>
        <para>
          <link linkend="gimp-view-soft-proof-view">Proof Colors</link>
        </para>
      </listitem>
      <listitem>
        <para>
          <link linkend="gimp-view-soft-proof-rendering-intent">Display
          Rendering Intent</link>
        </para>
      </listitem>
      <listitem>
        <para>
          <link linkend="gimp-view-soft-proof-black-point">Black Point
          Compensation</link>
        </para>
      </listitem>
      <listitem>
        <para>
          <link linkend="gimp-view-soft-mark-out-of-gamut">Mark Out Of
          Gamut Colors</link>
        </para>
      </listitem>
      <listitem>
        <para>
          <link linkend="gimp-view-color-management-reset">As in
          Preferences</link>
        </para>
      </listitem>
    </itemizedlist>
  </sect3>
</sect2>
