<?xml version='1.0' encoding='UTF-8'?>

<sect2 id='plug-in-vinvert' lang="en;fr">
  <title lang="en">Value invert</title>
  <title lang="fr">Inversion de la Valeur</title>
  
  <indexterm>
    <primary lang="en">Filter</primary>
    <secondary lang="en">Color</secondary>
    <tertiary lang="en">Value</tertiary>    
    
    <primary lang="fr">Filtre</primary>
    <tertiary lang="fr">Couleur</tertiary>
    <tertiary lang="fr">Valeur</tertiary>      
  </indexterm>

  <simplesect>
    <title lang="en">Overview</title>
    <title lang="fr">Généralités</title>
    <para lang="en">
      This filter is found in 
      <guimenuitem>Image&gt;Filters/Colors/<accel>V</accel>alue Invert</guimenuitem>
    </para>
    <para lang="en">
      This filter inverts Value (luminosity) of the active layer or selection. Hue and Saturation will 
      not be affected and color will be slightly different. If you want to invert Hue and Saturation also, 
      use 
      <guimenuitem>Image&gt;Layers/Colors/Invert</guimenuitem>.
    </para>
    <para lang="fr">
      Ce filtre se trouve à 
      <guimenuitem>Image&gt;Filtres/Couleurs/Inversion de <accel>v</accel>aleur</guimenuitem>
    </para>
    <para lang="fr">
      Ce filtre inverse la Valeur (luminosité) du calque courant ou de la sélection. La teinte et 
      la saturation ne sont pas affectées et la couleur restera la même, mais d'une nuance différente.
      Si vous voulez inverser aussi la Teinte et la Saturation, utilisez 
      <guimenuitem>Image&gt;Calques/Couleurs/Inverser</guimenuitem>. 																		     
  </para> 
  </simplesect>
  
  <simplesect>
    <title lang="en">Options</title>
    <title lang="fr">Options</title>
    <para lang="en">
      This filter has no option.
    </para>
    <para lang="fr">
      Ce filtre n'a pas d'option.
    </para>
  </simplesect>

</sect2>
